splitpdf_pro/__init__.py
splitpdf_pro/main.py
splitpdf_pro-1.0.1.dist-info/METADATA
splitpdf_pro-1.0.1.dist-info/WHEEL
splitpdf_pro-1.0.1.dist-info/entry_points.txt
splitpdf_pro-1.0.1.dist-info/top_level.txt
splitpdf_pro-1.0.1.dist-info/RECORD
