Metadata-Version: 2.1
Name: splitpdf-pro
Version: 1.0.1
Summary: A python package for split pdf
Home-page: https://github.com/jakbin/splitpdf-pro
Author: Jak Bin
Project-URL: Bug Tracker, https://github.com/jakbin/splitpdf-pro/issues
Keywords: pdf,python-pdf,splitpdf,pypdf,splitpdf-pro
Classifier: Programming Language :: Python :: 3
Classifier: License :: OSI Approved :: MIT License
Classifier: Operating System :: OS Independent
Requires-Python: >=3.6
Requires-Dist: PyPDF2
